<annotation>
    <folder>baidiaug</folder>
    <filename>DSC00986_0.jpg</filename>
    <path>inhouse\DSC00986_0.JPG</path>    
    <source>
        <database>Unknown</database>
    </source>
    <size>
        <width>4432</width>
        <height>3235</height>
        <depth>3</depth>
    </size>
    <segmented>0</segmented>
    <object>
        <name>1</name>
        <pose>Unspecified</pose>
        <truncated>1</truncated>
        <difficult>0</difficult>
        <bndbox>
            <xmin>4266</xmin>
            <ymin>2193</ymin>
            <xmax>4432</xmax>
            <ymax>2519</ymax>
        </bndbox>
    </object>
    <object>
        <name>13</name>
        <pose>Unspecified</pose>
        <truncated>1</truncated>
        <difficult>0</difficult>
        <bndbox>
            <xmin>819</xmin>
            <ymin>2111</ymin>
            <xmax>1138</xmax>
            <ymax>2491</ymax>
        </bndbox>
    </object>
    <object>
        <name>13</name>
        <pose>Unspecified</pose>
        <truncated>1</truncated>
        <difficult>0</difficult>
        <bndbox>
            <xmin>1119</xmin>
            <ymin>2085</ymin>
            <xmax>1317</xmax>
            <ymax>2371</ymax>
        </bndbox>
    </object>
    <object>
        <name>1</name>
        <pose>Unspecified</pose>
        <truncated>1</truncated>
        <difficult>0</difficult>
        <bndbox>
            <xmin>626</xmin>
            <ymin>1624</ymin>
            <xmax>1145</xmax>
            <ymax>2130</ymax>
        </bndbox>
    </object>
    <object>
        <name>1</name>
        <pose>Unspecified</pose>
        <truncated>1</truncated>
        <difficult>0</difficult>
        <bndbox>
            <xmin>1157</xmin>
            <ymin>1701</ymin>
            <xmax>1418</xmax>
            <ymax>1970</ymax>
        </bndbox>
    </object>
    <object>
        <name>1</name>
        <pose>Unspecified</pose>
        <truncated>1</truncated>
        <difficult>0</difficult>
        <bndbox>
            <xmin>919</xmin>
            <ymin>1430</ymin>
            <xmax>1240</xmax>
            <ymax>1687</ymax>
        </bndbox>
    </object>
    <object>
        <name>13</name>
        <pose>Unspecified</pose>
        <truncated>1</truncated>
        <difficult>0</difficult>
        <bndbox>
            <xmin>501</xmin>
            <ymin>1167</ymin>
            <xmax>902</xmax>
            <ymax>1516</ymax>
        </bndbox>
    </object>
    <object>
        <name>1</name>
        <pose>Unspecified</pose>
        <truncated>1</truncated>
        <difficult>0</difficult>
        <bndbox>
            <xmin>979</xmin>
            <ymin>1165</ymin>
            <xmax>1187</xmax>
            <ymax>1450</ymax>
        </bndbox>
    </object>
    <object>
        <name>1</name>
        <pose>Unspecified</pose>
        <truncated>1</truncated>
        <difficult>0</difficult>
        <bndbox>
            <xmin>1096</xmin>
            <ymin>1061</ymin>
            <xmax>1507</xmax>
            <ymax>1325</ymax>
        </bndbox>
    </object>
    <object>
        <name>13</name>
        <pose>Unspecified</pose>
        <truncated>1</truncated>
        <difficult>0</difficult>
        <bndbox>
            <xmin>1364</xmin>
            <ymin>677</ymin>
            <xmax>1813</xmax>
            <ymax>1132</ymax>
        </bndbox>
    </object>
    <object>
        <name>1</name>
        <pose>Unspecified</pose>
        <truncated>1</truncated>
        <difficult>0</difficult>
        <bndbox>
            <xmin>1255</xmin>
            <ymin>1276</ymin>
            <xmax>1648</xmax>
            <ymax>1566</ymax>
        </bndbox>
    </object>
    <object>
        <name>1</name>
        <pose>Unspecified</pose>
        <truncated>1</truncated>
        <difficult>0</difficult>
        <bndbox>
            <xmin>1587</xmin>
            <ymin>1090</ymin>
            <xmax>1833</xmax>
            <ymax>1452</ymax>
        </bndbox>
    </object>
    <object>
        <name>13</name>
        <pose>Unspecified</pose>
        <truncated>1</truncated>
        <difficult>0</difficult>
        <bndbox>
            <xmin>1541</xmin>
            <ymin>1967</ymin>
            <xmax>1891</xmax>
            <ymax>2422</ymax>
        </bndbox>
    </object>
    <object>
        <name>13</name>
        <pose>Unspecified</pose>
        <truncated>1</truncated>
        <difficult>0</difficult>
        <bndbox>
            <xmin>1517</xmin>
            <ymin>1713</ymin>
            <xmax>1845</xmax>
            <ymax>1949</ymax>
        </bndbox>
    </object>
    <object>
        <name>1</name>
        <pose>Unspecified</pose>
        <truncated>1</truncated>
        <difficult>0</difficult>
        <bndbox>
            <xmin>1762</xmin>
            <ymin>1508</ymin>
            <xmax>1934</xmax>
            <ymax>1828</ymax>
        </bndbox>
    </object>
    <object>
        <name>1</name>
        <pose>Unspecified</pose>
        <truncated>1</truncated>
        <difficult>0</difficult>
        <bndbox>
            <xmin>1977</xmin>
            <ymin>1802</ymin>
            <xmax>2206</xmax>
            <ymax>2071</ymax>
        </bndbox>
    </object>
    <object>
        <name>1</name>
        <pose>Unspecified</pose>
        <truncated>1</truncated>
        <difficult>0</difficult>
        <bndbox>
            <xmin>2141</xmin>
            <ymin>1567</ymin>
            <xmax>2360</xmax>
            <ymax>1771</ymax>
        </bndbox>
    </object>
    <object>
        <name>1</name>
        <pose>Unspecified</pose>
        <truncated>1</truncated>
        <difficult>0</difficult>
        <bndbox>
            <xmin>2198</xmin>
            <ymin>1741</ymin>
            <xmax>2481</xmax>
            <ymax>1908</ymax>
        </bndbox>
    </object>
    <object>
        <name>1</name>
        <pose>Unspecified</pose>
        <truncated>1</truncated>
        <difficult>0</difficult>
        <bndbox>
            <xmin>2143</xmin>
            <ymin>1895</ymin>
            <xmax>2363</xmax>
            <ymax>2192</ymax>
        </bndbox>
    </object>
    <object>
        <name>13</name>
        <pose>Unspecified</pose>
        <truncated>1</truncated>
        <difficult>0</difficult>
        <bndbox>
            <xmin>2735</xmin>
            <ymin>1218</ymin>
            <xmax>3130</xmax>
            <ymax>1591</ymax>
        </bndbox>
    </object>
    <object>
        <name>1</name>
        <pose>Unspecified</pose>
        <truncated>1</truncated>
        <difficult>0</difficult>
        <bndbox>
            <xmin>2398</xmin>
            <ymin>1096</ymin>
            <xmax>2819</xmax>
            <ymax>1397</ymax>
        </bndbox>
    </object>
    <object>
        <name>13</name>
        <pose>Unspecified</pose>
        <truncated>1</truncated>
        <difficult>0</difficult>
        <bndbox>
            <xmin>2885</xmin>
            <ymin>1637</ymin>
            <xmax>3085</xmax>
            <ymax>1781</ymax>
        </bndbox>
    </object>
    <object>
        <name>1</name>
        <pose>Unspecified</pose>
        <truncated>1</truncated>
        <difficult>0</difficult>
        <bndbox>
            <xmin>3216</xmin>
            <ymin>1725</ymin>
            <xmax>3343</xmax>
            <ymax>1972</ymax>
        </bndbox>
    </object>
    <object>
        <name>1</name>
        <pose>Unspecified</pose>
        <truncated>1</truncated>
        <difficult>0</difficult>
        <bndbox>
            <xmin>3178</xmin>
            <ymin>1448</ymin>
            <xmax>3340</xmax>
            <ymax>1658</ymax>
        </bndbox>
    </object>
    <object>
        <name>1</name>
        <pose>Unspecified</pose>
        <truncated>1</truncated>
        <difficult>0</difficult>
        <bndbox>
            <xmin>3439</xmin>
            <ymin>1588</ymin>
            <xmax>3699</xmax>
            <ymax>2002</ymax>
        </bndbox>
    </object>
    <object>
        <name>1</name>
        <pose>Unspecified</pose>
        <truncated>1</truncated>
        <difficult>0</difficult>
        <bndbox>
            <xmin>3534</xmin>
            <ymin>2048</ymin>
            <xmax>3724</xmax>
            <ymax>2374</ymax>
        </bndbox>
    </object>
    <object>
        <name>1</name>
        <pose>Unspecified</pose>
        <truncated>1</truncated>
        <difficult>0</difficult>
        <bndbox>
            <xmin>2885</xmin>
            <ymin>2087</ymin>
            <xmax>3227</xmax>
            <ymax>2336</ymax>
        </bndbox>
    </object>
    <object>
        <name>1</name>
        <pose>Unspecified</pose>
        <truncated>1</truncated>
        <difficult>0</difficult>
        <bndbox>
            <xmin>3297</xmin>
            <ymin>2249</ymin>
            <xmax>3548</xmax>
            <ymax>2717</ymax>
        </bndbox>
    </object>
    <object>
        <name>1</name>
        <pose>Unspecified</pose>
        <truncated>1</truncated>
        <difficult>0</difficult>
        <bndbox>
            <xmin>3129</xmin>
            <ymin>2327</ymin>
            <xmax>3358</xmax>
            <ymax>2710</ymax>
        </bndbox>
    </object>
    <object>
        <name>1</name>
        <pose>Unspecified</pose>
        <truncated>1</truncated>
        <difficult>0</difficult>
        <bndbox>
            <xmin>2621</xmin>
            <ymin>2265</ymin>
            <xmax>3150</xmax>
            <ymax>2739</ymax>
        </bndbox>
    </object>
</annotation>