<annotation>
    <folder>baidiaug</folder>
    <filename>DSC01419_0.jpg</filename>
    <path>inhouse\DSC01419_0.JPG</path>    
    <source>
        <database>Unknown</database>
    </source>
    <size>
        <width>3275</width>
        <height>3230</height>
        <depth>3</depth>
    </size>
    <segmented>0</segmented>
    <object>
        <name>13</name>
        <pose>Unspecified</pose>
        <truncated>1</truncated>
        <difficult>0</difficult>
        <bndbox>
            <xmin>335</xmin>
            <ymin>1166</ymin>
            <xmax>970</xmax>
            <ymax>1802</ymax>
        </bndbox>
    </object>
    <object>
        <name>13</name>
        <pose>Unspecified</pose>
        <truncated>1</truncated>
        <difficult>0</difficult>
        <bndbox>
            <xmin>1012</xmin>
            <ymin>1097</ymin>
            <xmax>1428</xmax>
            <ymax>1699</ymax>
        </bndbox>
    </object>
    <object>
        <name>13</name>
        <pose>Unspecified</pose>
        <truncated>1</truncated>
        <difficult>0</difficult>
        <bndbox>
            <xmin>1193</xmin>
            <ymin>806</ymin>
            <xmax>1734</xmax>
            <ymax>1283</ymax>
        </bndbox>
    </object>
    <object>
        <name>13</name>
        <pose>Unspecified</pose>
        <truncated>1</truncated>
        <difficult>0</difficult>
        <bndbox>
            <xmin>651</xmin>
            <ymin>400</ymin>
            <xmax>1163</xmax>
            <ymax>834</ymax>
        </bndbox>
    </object>
    <object>
        <name>13</name>
        <pose>Unspecified</pose>
        <truncated>1</truncated>
        <difficult>0</difficult>
        <bndbox>
            <xmin>337</xmin>
            <ymin>797</ymin>
            <xmax>993</xmax>
            <ymax>1136</ymax>
        </bndbox>
    </object>
    <object>
        <name>13</name>
        <pose>Unspecified</pose>
        <truncated>1</truncated>
        <difficult>0</difficult>
        <bndbox>
            <xmin>1511</xmin>
            <ymin>524</ymin>
            <xmax>1818</xmax>
            <ymax>993</ymax>
        </bndbox>
    </object>
    <object>
        <name>13</name>
        <pose>Unspecified</pose>
        <truncated>1</truncated>
        <difficult>0</difficult>
        <bndbox>
            <xmin>1038</xmin>
            <ymin>2198</ymin>
            <xmax>1276</xmax>
            <ymax>2521</ymax>
        </bndbox>
    </object>
    <object>
        <name>13</name>
        <pose>Unspecified</pose>
        <truncated>1</truncated>
        <difficult>0</difficult>
        <bndbox>
            <xmin>1295</xmin>
            <ymin>2218</ymin>
            <xmax>1580</xmax>
            <ymax>2501</ymax>
        </bndbox>
    </object>
    <object>
        <name>13</name>
        <pose>Unspecified</pose>
        <truncated>1</truncated>
        <difficult>0</difficult>
        <bndbox>
            <xmin>439</xmin>
            <ymin>2667</ymin>
            <xmax>764</xmax>
            <ymax>2972</ymax>
        </bndbox>
    </object>
    <object>
        <name>13</name>
        <pose>Unspecified</pose>
        <truncated>1</truncated>
        <difficult>0</difficult>
        <bndbox>
            <xmin>2087</xmin>
            <ymin>885</ymin>
            <xmax>2530</xmax>
            <ymax>1193</ymax>
        </bndbox>
    </object>
</annotation>