<annotation>
    <folder>baidiaug</folder>
    <filename>DSC01156_4.jpg</filename>
    <path>inhouse\DSC01156_4.JPG</path>    
    <source>
        <database>Unknown</database>
    </source>
    <size>
        <width>4651</width>
        <height>2401</height>
        <depth>3</depth>
    </size>
    <segmented>0</segmented>
    <object>
        <name>14</name>
        <pose>Unspecified</pose>
        <truncated>1</truncated>
        <difficult>0</difficult>
        <bndbox>
            <xmin>2841</xmin>
            <ymin>996</ymin>
            <xmax>3260</xmax>
            <ymax>1217</ymax>
        </bndbox>
    </object>
    <object>
        <name>14</name>
        <pose>Unspecified</pose>
        <truncated>1</truncated>
        <difficult>0</difficult>
        <bndbox>
            <xmin>2674</xmin>
            <ymin>1331</ymin>
            <xmax>2965</xmax>
            <ymax>1601</ymax>
        </bndbox>
    </object>
    <object>
        <name>14</name>
        <pose>Unspecified</pose>
        <truncated>1</truncated>
        <difficult>0</difficult>
        <bndbox>
            <xmin>2942</xmin>
            <ymin>368</ymin>
            <xmax>3510</xmax>
            <ymax>694</ymax>
        </bndbox>
    </object>
    <object>
        <name>14</name>
        <pose>Unspecified</pose>
        <truncated>1</truncated>
        <difficult>0</difficult>
        <bndbox>
            <xmin>2746</xmin>
            <ymin>570</ymin>
            <xmax>3061</xmax>
            <ymax>981</ymax>
        </bndbox>
    </object>
</annotation>