<annotation>
    <folder>baidiaug</folder>
    <filename>DSC00997_3.jpg</filename>
    <path>inhouse\DSC00997_3.JPG</path>    
    <source>
        <database>Unknown</database>
    </source>
    <size>
        <width>2028</width>
        <height>2684</height>
        <depth>3</depth>
    </size>
    <segmented>0</segmented>
    <object>
        <name>14</name>
        <pose>Unspecified</pose>
        <truncated>1</truncated>
        <difficult>0</difficult>
        <bndbox>
            <xmin>1259</xmin>
            <ymin>1648</ymin>
            <xmax>1795</xmax>
            <ymax>2083</ymax>
        </bndbox>
    </object>
    <object>
        <name>14</name>
        <pose>Unspecified</pose>
        <truncated>1</truncated>
        <difficult>0</difficult>
        <bndbox>
            <xmin>877</xmin>
            <ymin>1769</ymin>
            <xmax>1253</xmax>
            <ymax>2380</ymax>
        </bndbox>
    </object>
    <object>
        <name>14</name>
        <pose>Unspecified</pose>
        <truncated>1</truncated>
        <difficult>0</difficult>
        <bndbox>
            <xmin>1230</xmin>
            <ymin>1012</ymin>
            <xmax>1640</xmax>
            <ymax>1412</ymax>
        </bndbox>
    </object>
    <object>
        <name>14</name>
        <pose>Unspecified</pose>
        <truncated>1</truncated>
        <difficult>0</difficult>
        <bndbox>
            <xmin>753</xmin>
            <ymin>1493</ymin>
            <xmax>1121</xmax>
            <ymax>1751</ymax>
        </bndbox>
    </object>
    <object>
        <name>14</name>
        <pose>Unspecified</pose>
        <truncated>1</truncated>
        <difficult>0</difficult>
        <bndbox>
            <xmin>958</xmin>
            <ymin>944</ymin>
            <xmax>1407</xmax>
            <ymax>1241</ymax>
        </bndbox>
    </object>
    <object>
        <name>13</name>
        <pose>Unspecified</pose>
        <truncated>1</truncated>
        <difficult>0</difficult>
        <bndbox>
            <xmin>452</xmin>
            <ymin>73</ymin>
            <xmax>769</xmax>
            <ymax>405</ymax>
        </bndbox>
    </object>
    <object>
        <name>13</name>
        <pose>Unspecified</pose>
        <truncated>1</truncated>
        <difficult>0</difficult>
        <bndbox>
            <xmin>1520</xmin>
            <ymin>0</ymin>
            <xmax>1788</xmax>
            <ymax>151</ymax>
        </bndbox>
    </object>
    <object>
        <name>13</name>
        <pose>Unspecified</pose>
        <truncated>1</truncated>
        <difficult>0</difficult>
        <bndbox>
            <xmin>1016</xmin>
            <ymin>43</ymin>
            <xmax>1355</xmax>
            <ymax>295</ymax>
        </bndbox>
    </object>
</annotation>