<annotation>
    <folder>baidiaug</folder>
    <filename>DSC01117_2.jpg</filename>
    <path>inhouse\DSC01117_2.JPG</path>    
    <source>
        <database>Unknown</database>
    </source>
    <size>
        <width>4143</width>
        <height>1584</height>
        <depth>3</depth>
    </size>
    <segmented>0</segmented>
    <object>
        <name>14</name>
        <pose>Unspecified</pose>
        <truncated>1</truncated>
        <difficult>0</difficult>
        <bndbox>
            <xmin>2935</xmin>
            <ymin>472</ymin>
            <xmax>3250</xmax>
            <ymax>669</ymax>
        </bndbox>
    </object>
    <object>
        <name>14</name>
        <pose>Unspecified</pose>
        <truncated>1</truncated>
        <difficult>0</difficult>
        <bndbox>
            <xmin>3026</xmin>
            <ymin>299</ymin>
            <xmax>3237</xmax>
            <ymax>430</ymax>
        </bndbox>
    </object>
    <object>
        <name>14</name>
        <pose>Unspecified</pose>
        <truncated>1</truncated>
        <difficult>0</difficult>
        <bndbox>
            <xmin>1568</xmin>
            <ymin>132</ymin>
            <xmax>1790</xmax>
            <ymax>419</ymax>
        </bndbox>
    </object>
</annotation>