<annotation>
    <folder>baidiaug</folder>
    <filename>DSC01551_5.jpg</filename>
    <path>inhouse\DSC01551_5.JPG</path>    
    <source>
        <database>Unknown</database>
    </source>
    <size>
        <width>3736</width>
        <height>2922</height>
        <depth>3</depth>
    </size>
    <segmented>0</segmented>
    <object>
        <name>14</name>
        <pose>Unspecified</pose>
        <truncated>1</truncated>
        <difficult>0</difficult>
        <bndbox>
            <xmin>1376</xmin>
            <ymin>205</ymin>
            <xmax>2572</xmax>
            <ymax>928</ymax>
        </bndbox>
    </object>
    <object>
        <name>14</name>
        <pose>Unspecified</pose>
        <truncated>1</truncated>
        <difficult>0</difficult>
        <bndbox>
            <xmin>1235</xmin>
            <ymin>1337</ymin>
            <xmax>2575</xmax>
            <ymax>2483</ymax>
        </bndbox>
    </object>
    <object>
        <name>14</name>
        <pose>Unspecified</pose>
        <truncated>1</truncated>
        <difficult>0</difficult>
        <bndbox>
            <xmin>106</xmin>
            <ymin>1906</ymin>
            <xmax>623</xmax>
            <ymax>2756</ymax>
        </bndbox>
    </object>
    <object>
        <name>14</name>
        <pose>Unspecified</pose>
        <truncated>1</truncated>
        <difficult>0</difficult>
        <bndbox>
            <xmin>573</xmin>
            <ymin>1712</ymin>
            <xmax>1300</xmax>
            <ymax>2583</ymax>
        </bndbox>
    </object>
    <object>
        <name>14</name>
        <pose>Unspecified</pose>
        <truncated>1</truncated>
        <difficult>0</difficult>
        <bndbox>
            <xmin>1671</xmin>
            <ymin>2179</ymin>
            <xmax>3053</xmax>
            <ymax>2854</ymax>
        </bndbox>
    </object>
    <object>
        <name>14</name>
        <pose>Unspecified</pose>
        <truncated>1</truncated>
        <difficult>0</difficult>
        <bndbox>
            <xmin>2746</xmin>
            <ymin>0</ymin>
            <xmax>3292</xmax>
            <ymax>502</ymax>
        </bndbox>
    </object>
</annotation>