<annotation>
    <folder>baidiaug</folder>
    <filename>DSC01376_1.jpg</filename>
    <path>inhouse\DSC01376_1.JPG</path>    
    <source>
        <database>Unknown</database>
    </source>
    <size>
        <width>4189</width>
        <height>2951</height>
        <depth>3</depth>
    </size>
    <segmented>0</segmented>
    <object>
        <name>13</name>
        <pose>Unspecified</pose>
        <truncated>1</truncated>
        <difficult>0</difficult>
        <bndbox>
            <xmin>2053</xmin>
            <ymin>180</ymin>
            <xmax>2310</xmax>
            <ymax>418</ymax>
        </bndbox>
    </object>
    <object>
        <name>13</name>
        <pose>Unspecified</pose>
        <truncated>1</truncated>
        <difficult>0</difficult>
        <bndbox>
            <xmin>2840</xmin>
            <ymin>1678</ymin>
            <xmax>3109</xmax>
            <ymax>2065</ymax>
        </bndbox>
    </object>
    <object>
        <name>13</name>
        <pose>Unspecified</pose>
        <truncated>1</truncated>
        <difficult>0</difficult>
        <bndbox>
            <xmin>2977</xmin>
            <ymin>1487</ymin>
            <xmax>3323</xmax>
            <ymax>1640</ymax>
        </bndbox>
    </object>
</annotation>