<annotation>
    <folder>baidiaug</folder>
    <filename>DSC01491_5.jpg</filename>
    <path>inhouse\DSC01491_5.JPG</path>    
    <source>
        <database>Unknown</database>
    </source>
    <size>
        <width>3597</width>
        <height>3324</height>
        <depth>3</depth>
    </size>
    <segmented>0</segmented>
    <object>
        <name>13</name>
        <pose>Unspecified</pose>
        <truncated>1</truncated>
        <difficult>0</difficult>
        <bndbox>
            <xmin>2834</xmin>
            <ymin>1500</ymin>
            <xmax>3091</xmax>
            <ymax>1727</ymax>
        </bndbox>
    </object>
    <object>
        <name>13</name>
        <pose>Unspecified</pose>
        <truncated>1</truncated>
        <difficult>0</difficult>
        <bndbox>
            <xmin>2514</xmin>
            <ymin>3023</ymin>
            <xmax>2838</xmax>
            <ymax>3324</ymax>
        </bndbox>
    </object>
</annotation>