<annotation>
    <folder>baidiaug</folder>
    <filename>DSC01549_6.jpg</filename>
    <path>inhouse\DSC01549_6.JPG</path>    
    <source>
        <database>Unknown</database>
    </source>
    <size>
        <width>2946</width>
        <height>2551</height>
        <depth>3</depth>
    </size>
    <segmented>0</segmented>
    <object>
        <name>13</name>
        <pose>Unspecified</pose>
        <truncated>1</truncated>
        <difficult>0</difficult>
        <bndbox>
            <xmin>13</xmin>
            <ymin>1201</ymin>
            <xmax>636</xmax>
            <ymax>2088</ymax>
        </bndbox>
    </object>
    <object>
        <name>13</name>
        <pose>Unspecified</pose>
        <truncated>1</truncated>
        <difficult>0</difficult>
        <bndbox>
            <xmin>902</xmin>
            <ymin>907</ymin>
            <xmax>1822</xmax>
            <ymax>2050</ymax>
        </bndbox>
    </object>
</annotation>