<annotation>
    <folder>baidiaug</folder>
    <filename>fieldTMV (34)_5.jpg</filename>
    <path>inhouse\fieldTMV (34)_5.JPG</path>    
    <source>
        <database>Unknown</database>
    </source>
    <size>
        <width>2212</width>
        <height>2800</height>
        <depth>3</depth>
    </size>
    <segmented>0</segmented>
    <object>
        <name>13</name>
        <pose>Unspecified</pose>
        <truncated>1</truncated>
        <difficult>0</difficult>
        <bndbox>
            <xmin>155</xmin>
            <ymin>0</ymin>
            <xmax>2212</xmax>
            <ymax>2368</ymax>
        </bndbox>
    </object>
    <object>
        <name>13</name>
        <pose>Unspecified</pose>
        <truncated>1</truncated>
        <difficult>0</difficult>
        <bndbox>
            <xmin>611</xmin>
            <ymin>2083</ymin>
            <xmax>1315</xmax>
            <ymax>2800</ymax>
        </bndbox>
    </object>
    <object>
        <name>13</name>
        <pose>Unspecified</pose>
        <truncated>1</truncated>
        <difficult>0</difficult>
        <bndbox>
            <xmin>106</xmin>
            <ymin>1754</ymin>
            <xmax>728</xmax>
            <ymax>2381</ymax>
        </bndbox>
    </object>
    <object>
        <name>13</name>
        <pose>Unspecified</pose>
        <truncated>1</truncated>
        <difficult>0</difficult>
        <bndbox>
            <xmin>0</xmin>
            <ymin>756</ymin>
            <xmax>344</xmax>
            <ymax>1732</ymax>
        </bndbox>
    </object>
    <object>
        <name>13</name>
        <pose>Unspecified</pose>
        <truncated>1</truncated>
        <difficult>0</difficult>
        <bndbox>
            <xmin>0</xmin>
            <ymin>813</ymin>
            <xmax>803</xmax>
            <ymax>1623</ymax>
        </bndbox>
    </object>
</annotation>