<annotation>
    <folder>baidiaug</folder>
    <filename>field (2)_3.jpg</filename>
    <path>inhouse\field (2)_3.JPG</path>    
    <source>
        <database>Unknown</database>
    </source>
    <size>
        <width>2164</width>
        <height>2211</height>
        <depth>3</depth>
    </size>
    <segmented>0</segmented>
    <object>
        <name>13</name>
        <pose>Unspecified</pose>
        <truncated>1</truncated>
        <difficult>0</difficult>
        <bndbox>
            <xmin>670</xmin>
            <ymin>947</ymin>
            <xmax>1196</xmax>
            <ymax>1339</ymax>
        </bndbox>
    </object>
    <object>
        <name>14</name>
        <pose>Unspecified</pose>
        <truncated>1</truncated>
        <difficult>0</difficult>
        <bndbox>
            <xmin>1721</xmin>
            <ymin>0</ymin>
            <xmax>2164</xmax>
            <ymax>876</ymax>
        </bndbox>
    </object>
    <object>
        <name>13</name>
        <pose>Unspecified</pose>
        <truncated>1</truncated>
        <difficult>0</difficult>
        <bndbox>
            <xmin>357</xmin>
            <ymin>85</ymin>
            <xmax>718</xmax>
            <ymax>404</ymax>
        </bndbox>
    </object>
    <object>
        <name>14</name>
        <pose>Unspecified</pose>
        <truncated>1</truncated>
        <difficult>0</difficult>
        <bndbox>
            <xmin>727</xmin>
            <ymin>1417</ymin>
            <xmax>1462</xmax>
            <ymax>2211</ymax>
        </bndbox>
    </object>
    <object>
        <name>14</name>
        <pose>Unspecified</pose>
        <truncated>1</truncated>
        <difficult>0</difficult>
        <bndbox>
            <xmin>857</xmin>
            <ymin>474</ymin>
            <xmax>1394</xmax>
            <ymax>849</ymax>
        </bndbox>
    </object>
    <object>
        <name>13</name>
        <pose>Unspecified</pose>
        <truncated>1</truncated>
        <difficult>0</difficult>
        <bndbox>
            <xmin>494</xmin>
            <ymin>593</ymin>
            <xmax>805</xmax>
            <ymax>847</ymax>
        </bndbox>
    </object>
</annotation>