<annotation>
    <folder>baidiaug</folder>
    <filename>IMG_2782_5.jpg</filename>
    <path>inhouse\IMG_2782_5.JPG</path>    
    <source>
        <database>Unknown</database>
    </source>
    <size>
        <width>2015</width>
        <height>2513</height>
        <depth>3</depth>
    </size>
    <segmented>0</segmented>
    <object>
        <name>13</name>
        <pose>Unspecified</pose>
        <truncated>1</truncated>
        <difficult>0</difficult>
        <bndbox>
            <xmin>157</xmin>
            <ymin>796</ymin>
            <xmax>1022</xmax>
            <ymax>1349</ymax>
        </bndbox>
    </object>
    <object>
        <name>13</name>
        <pose>Unspecified</pose>
        <truncated>1</truncated>
        <difficult>0</difficult>
        <bndbox>
            <xmin>928</xmin>
            <ymin>388</ymin>
            <xmax>1544</xmax>
            <ymax>1099</ymax>
        </bndbox>
    </object>
    <object>
        <name>13</name>
        <pose>Unspecified</pose>
        <truncated>1</truncated>
        <difficult>0</difficult>
        <bndbox>
            <xmin>587</xmin>
            <ymin>1393</ymin>
            <xmax>1437</xmax>
            <ymax>2163</ymax>
        </bndbox>
    </object>
    <object>
        <name>13</name>
        <pose>Unspecified</pose>
        <truncated>1</truncated>
        <difficult>0</difficult>
        <bndbox>
            <xmin>1351</xmin>
            <ymin>1599</ymin>
            <xmax>1865</xmax>
            <ymax>2432</ymax>
        </bndbox>
    </object>
    <object>
        <name>13</name>
        <pose>Unspecified</pose>
        <truncated>1</truncated>
        <difficult>0</difficult>
        <bndbox>
            <xmin>1615</xmin>
            <ymin>458</ymin>
            <xmax>2015</xmax>
            <ymax>1136</ymax>
        </bndbox>
    </object>
    <object>
        <name>13</name>
        <pose>Unspecified</pose>
        <truncated>1</truncated>
        <difficult>0</difficult>
        <bndbox>
            <xmin>1665</xmin>
            <ymin>2203</ymin>
            <xmax>2015</xmax>
            <ymax>2513</ymax>
        </bndbox>
    </object>
</annotation>