<annotation>
    <folder>baidiaug</folder>
    <filename>IMG_2338_2.jpg</filename>
    <path>inhouse\IMG_2338_2.JPG</path>    
    <source>
        <database>Unknown</database>
    </source>
    <size>
        <width>2435</width>
        <height>1804</height>
        <depth>3</depth>
    </size>
    <segmented>0</segmented>
    <object>
        <name>13</name>
        <pose>Unspecified</pose>
        <truncated>1</truncated>
        <difficult>0</difficult>
        <bndbox>
            <xmin>1952</xmin>
            <ymin>305</ymin>
            <xmax>2435</xmax>
            <ymax>981</ymax>
        </bndbox>
    </object>
    <object>
        <name>13</name>
        <pose>Unspecified</pose>
        <truncated>1</truncated>
        <difficult>0</difficult>
        <bndbox>
            <xmin>295</xmin>
            <ymin>541</ymin>
            <xmax>852</xmax>
            <ymax>866</ymax>
        </bndbox>
    </object>
    <object>
        <name>13</name>
        <pose>Unspecified</pose>
        <truncated>1</truncated>
        <difficult>0</difficult>
        <bndbox>
            <xmin>1668</xmin>
            <ymin>0</ymin>
            <xmax>2255</xmax>
            <ymax>213</ymax>
        </bndbox>
    </object>
    <object>
        <name>13</name>
        <pose>Unspecified</pose>
        <truncated>1</truncated>
        <difficult>0</difficult>
        <bndbox>
            <xmin>188</xmin>
            <ymin>894</ymin>
            <xmax>782</xmax>
            <ymax>1190</ymax>
        </bndbox>
    </object>
    <object>
        <name>13</name>
        <pose>Unspecified</pose>
        <truncated>1</truncated>
        <difficult>0</difficult>
        <bndbox>
            <xmin>2098</xmin>
            <ymin>1534</ymin>
            <xmax>2435</xmax>
            <ymax>1804</ymax>
        </bndbox>
    </object>
</annotation>