<annotation>
    <folder>baidiaug</folder>
    <filename>IMG_7311_2.jpg</filename>
    <path>inhouse\IMG_7311_2.JPG</path>    
    <source>
        <database>Unknown</database>
    </source>
    <size>
        <width>1464</width>
        <height>2244</height>
        <depth>3</depth>
    </size>
    <segmented>0</segmented>
    <object>
        <name>14</name>
        <pose>Unspecified</pose>
        <truncated>1</truncated>
        <difficult>0</difficult>
        <bndbox>
            <xmin>423</xmin>
            <ymin>0</ymin>
            <xmax>795</xmax>
            <ymax>470</ymax>
        </bndbox>
    </object>
    <object>
        <name>14</name>
        <pose>Unspecified</pose>
        <truncated>1</truncated>
        <difficult>0</difficult>
        <bndbox>
            <xmin>750</xmin>
            <ymin>521</ymin>
            <xmax>1256</xmax>
            <ymax>1077</ymax>
        </bndbox>
    </object>
    <object>
        <name>14</name>
        <pose>Unspecified</pose>
        <truncated>1</truncated>
        <difficult>0</difficult>
        <bndbox>
            <xmin>318</xmin>
            <ymin>472</ymin>
            <xmax>596</xmax>
            <ymax>782</ymax>
        </bndbox>
    </object>
    <object>
        <name>14</name>
        <pose>Unspecified</pose>
        <truncated>1</truncated>
        <difficult>0</difficult>
        <bndbox>
            <xmin>0</xmin>
            <ymin>841</ymin>
            <xmax>243</xmax>
            <ymax>1446</ymax>
        </bndbox>
    </object>
    <object>
        <name>14</name>
        <pose>Unspecified</pose>
        <truncated>1</truncated>
        <difficult>0</difficult>
        <bndbox>
            <xmin>1105</xmin>
            <ymin>78</ymin>
            <xmax>1315</xmax>
            <ymax>439</ymax>
        </bndbox>
    </object>
    <object>
        <name>14</name>
        <pose>Unspecified</pose>
        <truncated>1</truncated>
        <difficult>0</difficult>
        <bndbox>
            <xmin>1095</xmin>
            <ymin>1535</ymin>
            <xmax>1401</xmax>
            <ymax>1994</ymax>
        </bndbox>
    </object>
    <object>
        <name>14</name>
        <pose>Unspecified</pose>
        <truncated>1</truncated>
        <difficult>0</difficult>
        <bndbox>
            <xmin>658</xmin>
            <ymin>1459</ymin>
            <xmax>914</xmax>
            <ymax>1648</ymax>
        </bndbox>
    </object>
    <object>
        <name>14</name>
        <pose>Unspecified</pose>
        <truncated>1</truncated>
        <difficult>0</difficult>
        <bndbox>
            <xmin>942</xmin>
            <ymin>1153</ymin>
            <xmax>1241</xmax>
            <ymax>1526</ymax>
        </bndbox>
    </object>
    <object>
        <name>14</name>
        <pose>Unspecified</pose>
        <truncated>1</truncated>
        <difficult>0</difficult>
        <bndbox>
            <xmin>713</xmin>
            <ymin>1802</ymin>
            <xmax>1063</xmax>
            <ymax>2191</ymax>
        </bndbox>
    </object>
</annotation>