<annotation>
    <folder>baidiaug</folder>
    <filename>IMG_7385_2.jpg</filename>
    <path>inhouse\IMG_7385_2.JPG</path>    
    <source>
        <database>Unknown</database>
    </source>
    <size>
        <width>2276</width>
        <height>2024</height>
        <depth>3</depth>
    </size>
    <segmented>0</segmented>
    <object>
        <name>14</name>
        <pose>Unspecified</pose>
        <truncated>1</truncated>
        <difficult>0</difficult>
        <bndbox>
            <xmin>1885</xmin>
            <ymin>1842</ymin>
            <xmax>2234</xmax>
            <ymax>2024</ymax>
        </bndbox>
    </object>
    <object>
        <name>14</name>
        <pose>Unspecified</pose>
        <truncated>1</truncated>
        <difficult>0</difficult>
        <bndbox>
            <xmin>71</xmin>
            <ymin>91</ymin>
            <xmax>647</xmax>
            <ymax>293</ymax>
        </bndbox>
    </object>
    <object>
        <name>14</name>
        <pose>Unspecified</pose>
        <truncated>1</truncated>
        <difficult>0</difficult>
        <bndbox>
            <xmin>382</xmin>
            <ymin>717</ymin>
            <xmax>676</xmax>
            <ymax>989</ymax>
        </bndbox>
    </object>
    <object>
        <name>14</name>
        <pose>Unspecified</pose>
        <truncated>1</truncated>
        <difficult>0</difficult>
        <bndbox>
            <xmin>722</xmin>
            <ymin>285</ymin>
            <xmax>1085</xmax>
            <ymax>896</ymax>
        </bndbox>
    </object>
    <object>
        <name>14</name>
        <pose>Unspecified</pose>
        <truncated>1</truncated>
        <difficult>0</difficult>
        <bndbox>
            <xmin>0</xmin>
            <ymin>782</ymin>
            <xmax>150</xmax>
            <ymax>1028</ymax>
        </bndbox>
    </object>
</annotation>