<annotation>
    <folder>baidiaug</folder>
    <filename>IMG_3029_0.jpg</filename>
    <path>inhouse\IMG_3029_0.JPG</path>    
    <source>
        <database>Unknown</database>
    </source>
    <size>
        <width>2900</width>
        <height>2498</height>
        <depth>3</depth>
    </size>
    <segmented>0</segmented>
    <object>
        <name>14</name>
        <pose>Unspecified</pose>
        <truncated>1</truncated>
        <difficult>0</difficult>
        <bndbox>
            <xmin>1213</xmin>
            <ymin>1539</ymin>
            <xmax>2286</xmax>
            <ymax>2498</ymax>
        </bndbox>
    </object>
    <object>
        <name>14</name>
        <pose>Unspecified</pose>
        <truncated>1</truncated>
        <difficult>0</difficult>
        <bndbox>
            <xmin>652</xmin>
            <ymin>1078</ymin>
            <xmax>2139</xmax>
            <ymax>1488</ymax>
        </bndbox>
    </object>
    <object>
        <name>14</name>
        <pose>Unspecified</pose>
        <truncated>1</truncated>
        <difficult>0</difficult>
        <bndbox>
            <xmin>509</xmin>
            <ymin>1262</ymin>
            <xmax>927</xmax>
            <ymax>2047</ymax>
        </bndbox>
    </object>
    <object>
        <name>14</name>
        <pose>Unspecified</pose>
        <truncated>1</truncated>
        <difficult>0</difficult>
        <bndbox>
            <xmin>128</xmin>
            <ymin>1279</ymin>
            <xmax>412</xmax>
            <ymax>1851</ymax>
        </bndbox>
    </object>
    <object>
        <name>14</name>
        <pose>Unspecified</pose>
        <truncated>1</truncated>
        <difficult>0</difficult>
        <bndbox>
            <xmin>213</xmin>
            <ymin>714</ymin>
            <xmax>401</xmax>
            <ymax>1203</ymax>
        </bndbox>
    </object>
    <object>
        <name>14</name>
        <pose>Unspecified</pose>
        <truncated>1</truncated>
        <difficult>0</difficult>
        <bndbox>
            <xmin>1415</xmin>
            <ymin>0</ymin>
            <xmax>1683</xmax>
            <ymax>293</ymax>
        </bndbox>
    </object>
    <object>
        <name>14</name>
        <pose>Unspecified</pose>
        <truncated>1</truncated>
        <difficult>0</difficult>
        <bndbox>
            <xmin>1183</xmin>
            <ymin>242</ymin>
            <xmax>1574</xmax>
            <ymax>528</ymax>
        </bndbox>
    </object>
    <object>
        <name>14</name>
        <pose>Unspecified</pose>
        <truncated>1</truncated>
        <difficult>0</difficult>
        <bndbox>
            <xmin>1693</xmin>
            <ymin>0</ymin>
            <xmax>2200</xmax>
            <ymax>189</ymax>
        </bndbox>
    </object>
    <object>
        <name>14</name>
        <pose>Unspecified</pose>
        <truncated>1</truncated>
        <difficult>0</difficult>
        <bndbox>
            <xmin>528</xmin>
            <ymin>810</ymin>
            <xmax>751</xmax>
            <ymax>1098</ymax>
        </bndbox>
    </object>
</annotation>