<annotation>
    <folder>baidiaug</folder>
    <filename>IMG_2270_3.jpg</filename>
    <path>inhouse\IMG_2270_3.JPG</path>    
    <source>
        <database>Unknown</database>
    </source>
    <size>
        <width>2384</width>
        <height>1532</height>
        <depth>3</depth>
    </size>
    <segmented>0</segmented>
    <object>
        <name>14</name>
        <pose>Unspecified</pose>
        <truncated>1</truncated>
        <difficult>0</difficult>
        <bndbox>
            <xmin>1137</xmin>
            <ymin>82</ymin>
            <xmax>1442</xmax>
            <ymax>426</ymax>
        </bndbox>
    </object>
    <object>
        <name>14</name>
        <pose>Unspecified</pose>
        <truncated>1</truncated>
        <difficult>0</difficult>
        <bndbox>
            <xmin>1959</xmin>
            <ymin>318</ymin>
            <xmax>2347</xmax>
            <ymax>682</ymax>
        </bndbox>
    </object>
    <object>
        <name>14</name>
        <pose>Unspecified</pose>
        <truncated>1</truncated>
        <difficult>0</difficult>
        <bndbox>
            <xmin>1401</xmin>
            <ymin>67</ymin>
            <xmax>1873</xmax>
            <ymax>537</ymax>
        </bndbox>
    </object>
    <object>
        <name>14</name>
        <pose>Unspecified</pose>
        <truncated>1</truncated>
        <difficult>0</difficult>
        <bndbox>
            <xmin>944</xmin>
            <ymin>938</ymin>
            <xmax>1385</xmax>
            <ymax>1397</ymax>
        </bndbox>
    </object>
</annotation>