<annotation>
    <folder>baidiaug</folder>
    <filename>IMG_3026_6.jpg</filename>
    <path>inhouse\IMG_3026_6.JPG</path>    
    <source>
        <database>Unknown</database>
    </source>
    <size>
        <width>2519</width>
        <height>3290</height>
        <depth>3</depth>
    </size>
    <segmented>0</segmented>
    <object>
        <name>13</name>
        <pose>Unspecified</pose>
        <truncated>1</truncated>
        <difficult>0</difficult>
        <bndbox>
            <xmin>812</xmin>
            <ymin>902</ymin>
            <xmax>1907</xmax>
            <ymax>2655</ymax>
        </bndbox>
    </object>
    <object>
        <name>13</name>
        <pose>Unspecified</pose>
        <truncated>1</truncated>
        <difficult>0</difficult>
        <bndbox>
            <xmin>1549</xmin>
            <ymin>0</ymin>
            <xmax>2519</xmax>
            <ymax>926</ymax>
        </bndbox>
    </object>
    <object>
        <name>13</name>
        <pose>Unspecified</pose>
        <truncated>1</truncated>
        <difficult>0</difficult>
        <bndbox>
            <xmin>265</xmin>
            <ymin>0</ymin>
            <xmax>1236</xmax>
            <ymax>560</ymax>
        </bndbox>
    </object>
    <object>
        <name>13</name>
        <pose>Unspecified</pose>
        <truncated>1</truncated>
        <difficult>0</difficult>
        <bndbox>
            <xmin>0</xmin>
            <ymin>2226</ymin>
            <xmax>344</xmax>
            <ymax>2659</ymax>
        </bndbox>
    </object>
    <object>
        <name>13</name>
        <pose>Unspecified</pose>
        <truncated>1</truncated>
        <difficult>0</difficult>
        <bndbox>
            <xmin>806</xmin>
            <ymin>2659</ymin>
            <xmax>1409</xmax>
            <ymax>3046</ymax>
        </bndbox>
    </object>
    <object>
        <name>13</name>
        <pose>Unspecified</pose>
        <truncated>1</truncated>
        <difficult>0</difficult>
        <bndbox>
            <xmin>0</xmin>
            <ymin>519</ymin>
            <xmax>233</xmax>
            <ymax>1103</ymax>
        </bndbox>
    </object>
    <object>
        <name>13</name>
        <pose>Unspecified</pose>
        <truncated>1</truncated>
        <difficult>0</difficult>
        <bndbox>
            <xmin>361</xmin>
            <ymin>715</ymin>
            <xmax>677</xmax>
            <ymax>1019</ymax>
        </bndbox>
    </object>
</annotation>