<annotation>
    <folder>baidiaug</folder>
    <filename>IMG_2616_1.jpg</filename>
    <path>inhouse\IMG_2616_1.JPG</path>    
    <source>
        <database>Unknown</database>
    </source>
    <size>
        <width>2773</width>
        <height>2421</height>
        <depth>3</depth>
    </size>
    <segmented>0</segmented>
    <object>
        <name>13</name>
        <pose>Unspecified</pose>
        <truncated>1</truncated>
        <difficult>0</difficult>
        <bndbox>
            <xmin>949</xmin>
            <ymin>0</ymin>
            <xmax>1806</xmax>
            <ymax>1215</ymax>
        </bndbox>
    </object>
    <object>
        <name>13</name>
        <pose>Unspecified</pose>
        <truncated>1</truncated>
        <difficult>0</difficult>
        <bndbox>
            <xmin>1587</xmin>
            <ymin>742</ymin>
            <xmax>2773</xmax>
            <ymax>1817</ymax>
        </bndbox>
    </object>
    <object>
        <name>13</name>
        <pose>Unspecified</pose>
        <truncated>1</truncated>
        <difficult>0</difficult>
        <bndbox>
            <xmin>20</xmin>
            <ymin>594</ymin>
            <xmax>1019</xmax>
            <ymax>1732</ymax>
        </bndbox>
    </object>
</annotation>