<annotation>
    <folder>baidiaug</folder>
    <filename>IMG_2819_6.jpg</filename>
    <path>inhouse\IMG_2819_6.JPG</path>    
    <source>
        <database>Unknown</database>
    </source>
    <size>
        <width>2709</width>
        <height>3116</height>
        <depth>3</depth>
    </size>
    <segmented>0</segmented>
    <object>
        <name>13</name>
        <pose>Unspecified</pose>
        <truncated>1</truncated>
        <difficult>0</difficult>
        <bndbox>
            <xmin>1416</xmin>
            <ymin>702</ymin>
            <xmax>2478</xmax>
            <ymax>2354</ymax>
        </bndbox>
    </object>
    <object>
        <name>13</name>
        <pose>Unspecified</pose>
        <truncated>1</truncated>
        <difficult>0</difficult>
        <bndbox>
            <xmin>0</xmin>
            <ymin>518</ymin>
            <xmax>1249</xmax>
            <ymax>2097</ymax>
        </bndbox>
    </object>
    <object>
        <name>13</name>
        <pose>Unspecified</pose>
        <truncated>1</truncated>
        <difficult>0</difficult>
        <bndbox>
            <xmin>968</xmin>
            <ymin>73</ymin>
            <xmax>1768</xmax>
            <ymax>748</ymax>
        </bndbox>
    </object>
    <object>
        <name>13</name>
        <pose>Unspecified</pose>
        <truncated>1</truncated>
        <difficult>0</difficult>
        <bndbox>
            <xmin>878</xmin>
            <ymin>1797</ymin>
            <xmax>1354</xmax>
            <ymax>2368</ymax>
        </bndbox>
    </object>
    <object>
        <name>13</name>
        <pose>Unspecified</pose>
        <truncated>1</truncated>
        <difficult>0</difficult>
        <bndbox>
            <xmin>1815</xmin>
            <ymin>2573</ymin>
            <xmax>2616</xmax>
            <ymax>3049</ymax>
        </bndbox>
    </object>
</annotation>