<annotation>
    <folder>baidiaug</folder>
    <filename>IMG_2716_0.jpg</filename>
    <path>inhouse\IMG_2716_0.JPG</path>    
    <source>
        <database>Unknown</database>
    </source>
    <size>
        <width>2262</width>
        <height>2175</height>
        <depth>3</depth>
    </size>
    <segmented>0</segmented>
    <object>
        <name>14</name>
        <pose>Unspecified</pose>
        <truncated>1</truncated>
        <difficult>0</difficult>
        <bndbox>
            <xmin>8</xmin>
            <ymin>373</ymin>
            <xmax>1184</xmax>
            <ymax>2175</ymax>
        </bndbox>
    </object>
    <object>
        <name>14</name>
        <pose>Unspecified</pose>
        <truncated>1</truncated>
        <difficult>0</difficult>
        <bndbox>
            <xmin>1030</xmin>
            <ymin>0</ymin>
            <xmax>2262</xmax>
            <ymax>880</ymax>
        </bndbox>
    </object>
    <object>
        <name>14</name>
        <pose>Unspecified</pose>
        <truncated>1</truncated>
        <difficult>0</difficult>
        <bndbox>
            <xmin>91</xmin>
            <ymin>1363</ymin>
            <xmax>471</xmax>
            <ymax>2140</ymax>
        </bndbox>
    </object>
</annotation>